honeycomb_rds_client/__init__.py
honeycomb_rds_client/core.py
honeycomb_rds_client/log.py
wf_honeycomb_rds_client-0.3.3.dist-info/LICENSE
wf_honeycomb_rds_client-0.3.3.dist-info/METADATA
wf_honeycomb_rds_client-0.3.3.dist-info/WHEEL
wf_honeycomb_rds_client-0.3.3.dist-info/RECORD
