Metadata-Version: 2.1
Name: wf-honeycomb-rds-client
Version: 0.3.3
Summary: A client for communicating with the RDS database underlying Honeycomb
Home-page: https://github.com/WildflowerSchools/wf-honeycomb-rds-client
License: MIT
Author: Theodore Quinn
Author-email: ted.quinn@wildflowerschools.org
Maintainer: Theodore Quinn
Maintainer-email: ted.quinn@wildflowerschools.org
Requires-Python: >=3.8,<4.0
Classifier: Intended Audience :: Developers
Classifier: License :: OSI Approved :: MIT License
Classifier: Operating System :: OS Independent
Classifier: Programming Language :: Python
Classifier: Programming Language :: Python :: 3
Classifier: Programming Language :: Python :: 3.8
Classifier: Programming Language :: Python :: 3.9
Classifier: Programming Language :: Python :: 3.10
Classifier: Programming Language :: Python :: 3.11
Requires-Dist: pandas (>=1.5)
Requires-Dist: pydantic (>=1.8)
Requires-Dist: toml (>=0.10.2,<0.11.0)
Requires-Dist: wf-honeycomb-io (>=2.1)
Requires-Dist: wf-postgres-client (>=0.1.0)
Project-URL: Repository, https://github.com/WildflowerSchools/wf-honeycomb-rds-client
